python_typeflow-0.13.6.dist-info/licenses/LICENSE
typeflow/__init__.py
typeflow/__main__.py
typeflow/config.py
typeflow/converters.py
typeflow/core.py
typeflow/types.py
python_typeflow-0.13.6.dist-info/METADATA
python_typeflow-0.13.6.dist-info/WHEEL
python_typeflow-0.13.6.dist-info/entry_points.txt
python_typeflow-0.13.6.dist-info/top_level.txt
python_typeflow-0.13.6.dist-info/RECORD
