Metadata-Version: 2.4
Name: python-typeflow
Version: 0.13.6
Summary: Seamlessly handle type conversion during operations in Python
Home-page: https://github.com/magi8101/typeflow
Author: Magi Sharma
Author-email: sharmamagi0@gmail.com
Classifier: Development Status :: 4 - Beta
Classifier: Intended Audience :: Developers
Classifier: License :: OSI Approved :: MIT License
Classifier: Topic :: Software Development :: Libraries :: Python Modules
Requires-Python: >3.0
License-File: LICENSE
Dynamic: author
Dynamic: author-email
Dynamic: classifier
Dynamic: description
Dynamic: description-content-type
Dynamic: home-page
Dynamic: license-file
Dynamic: requires-python
Dynamic: summary
